abl/__init__.py
abl/__version__.py
abl/bridge/__init__.py
abl/bridge/base_bridge.py
abl/bridge/simple_bridge.py
abl/data/__init__.py
abl/data/evaluation/__init__.py
abl/data/evaluation/base_metric.py
abl/data/evaluation/reasoning_metric.py
abl/data/evaluation/symbol_accuracy.py
abl/data/structures/__init__.py
abl/data/structures/base_data_element.py
abl/data/structures/list_data.py
abl/learning/__init__.py
abl/learning/abl_model.py
abl/learning/basic_nn.py
abl/learning/torch_dataset/__init__.py
abl/learning/torch_dataset/classification_dataset.py
abl/learning/torch_dataset/prediction_dataset.py
abl/learning/torch_dataset/regression_dataset.py
abl/reasoning/__init__.py
abl/reasoning/kb.py
abl/reasoning/reasoner.py
abl/utils/__init__.py
abl/utils/cache.py
abl/utils/logger.py
abl/utils/manager.py
abl/utils/utils.py
abl_test-0.1.4.dist-info/LICENSE
abl_test-0.1.4.dist-info/METADATA
abl_test-0.1.4.dist-info/WHEEL
abl_test-0.1.4.dist-info/top_level.txt
abl_test-0.1.4.dist-info/RECORD
