Metadata-Version: 2.1
Name: abl-test
Version: 0.1.4
Summary: ABL-Package
Author: LAMDA 2023
License: MIT Licence
Project-URL: Homepage, https://github.com/AbductiveLearning/ABL-Package
Project-URL: Issues, https://github.com/AbductiveLearning/ABL-Package/issues
Classifier: Programming Language :: Python :: 3
Classifier: License :: OSI Approved :: MIT License
Classifier: Operating System :: OS Independent
Requires-Python: >=3.6
License-File: LICENSE
Requires-Dist: numpy
Requires-Dist: pyswip ==0.2.9
Requires-Dist: torch
Requires-Dist: torchvision
Requires-Dist: zoopt
Requires-Dist: termcolor
